[
    {
        "type": "cover",
        "value": ""
    },
    {
        "type": "title",
        "value": "中国饭店业发展大会"
    },
    {
        "type": "p",
        "value": "2019年4月10日-12日，由世界旅游联盟、湖南省文化和旅游厅指导，湖南省旅游饭店协会、浙江省饭店业协会、山东省旅游饭店协会、广东酒店行业协会、中国饭店品质联盟联合主办，20个主要省市旅游饭店协会协办的“第二届中国饭店业发展大会”在长沙举办。"
    },
    {
        "type": "p",
        "value": "来自中国文旅行业的政、产、学、研等领域的知名机构和产业链高层共1500名代表参加会议，近60名全国业界专家论道，研究行业焦点问题，聚众智，汇合力，携手谱写新时代中国饭店业高质量发展新篇章。"
    },
    {
        "type": "img",
        "value": "img/03_zgfdfzdh_01.jpg"
    },
    {
        "type": "img",
        "value": "img/03_zgfdfzdh_02.jpg"
    },
    {
        "type": "img",
        "value": "img/03_zgfdfzdh_03.jpg"
    },
    {
        "type": "img",
        "value": "img/03_zgfdfzdh_04.jpg"
    },
    {
        "type": "img",
        "value": "img/03_zgfdfzdh_05.jpg"
    },
    {
        "type": "img",
        "value": "img/03_zgfdfzdh_06.jpg"
    },
    {
        "type": "img",
        "value": "img/03_zgfdfzdh_07.jpg"
    }
]
